[
  [
    { "label": "q" },
    { "label": "w" },
    { "label": "f" },
    { "label": "p" },
    { "label": "b" },
    { "label": "j" },
    { "label": "l" },
    { "label": "u" },
    { "label": "y" },
    { "$": "shift_state_selector",
      "shiftedManual": { "label": ":" },
      "default": { "label": ";", "popup": { "main": { "label": ":" } } }
    }
  ],
  [
    { "label": "a" },
    { "label": "r" },
    { "label": "s" },
    { "label": "t" },
    { "label": "g" },
    { "label": "m" },
    { "label": "n" },
    { "label": "e" },
    { "label": "i" },
    { "label": "o", "popup": { "main": { "label": "…" } } }
  ],
  [
    { "label": "z" },
    { "label": "x" },
    { "label": "c" },
    { "label": "d" },
    { "label": "v" },
    { "label": "k" },
    { "label": "h" }
  ]
]
